dcg_service/__init__.py
dcg_service/core/__init__.py
dcg_service/core/authentication.py
dcg_service/core/constants.py
dcg_service/core/encryption.py
dcg_service/core/events.py
dcg_service/core/exceptions.py
dcg_service/core/filters.py
dcg_service/core/logger.py
dcg_service/core/permissions.py
dcg_service/core/request_client.py
dcg_service/core/response.py
dcg_service/core/services.py
dcg_service/core/utils.py
dcg_service/core/core/__init__.py
dcg_service/core/core/authentication.py
dcg_service/core/core/constants.py
dcg_service/core/core/encryption.py
dcg_service/core/core/events.py
dcg_service/core/core/exceptions.py
dcg_service/core/core/filters.py
dcg_service/core/core/logger.py
dcg_service/core/core/permissions.py
dcg_service/core/core/request_client.py
dcg_service/core/core/response.py
dcg_service/core/core/services.py
dcg_service/core/core/utils.py
dcg_service-1.9.2.dist-info/LICENCE
dcg_service-1.9.2.dist-info/METADATA
dcg_service-1.9.2.dist-info/WHEEL
dcg_service-1.9.2.dist-info/top_level.txt
dcg_service-1.9.2.dist-info/RECORD
